mgraph_ai_service_html/__init__.py
mgraph_ai_service_html/config.py
mgraph_ai_service_html/html__fast_api/Html_Service__Fast_API.py
mgraph_ai_service_html/html__fast_api/__init__.py
mgraph_ai_service_html/html__fast_api/core/Html__Direct__Transformations.py
mgraph_ai_service_html/html__fast_api/core/Html__Extract_Text_Nodes.py
mgraph_ai_service_html/html__fast_api/core/Html__Hash__Transformations.py
mgraph_ai_service_html/html__fast_api/core/__init__.py
mgraph_ai_service_html/html__fast_api/routes/Routes__Dict.py
mgraph_ai_service_html/html__fast_api/routes/Routes__Hashes.py
mgraph_ai_service_html/html__fast_api/routes/Routes__Html.py
mgraph_ai_service_html/html__fast_api/routes/__init__.py
mgraph_ai_service_html/html__fast_api/schemas/__init__.py
mgraph_ai_service_html/html__fast_api/schemas/dict/Schema__Dict__To__Html__Request.py
mgraph_ai_service_html/html__fast_api/schemas/dict/Schema__Dict__To__Text__Nodes__Request.py
mgraph_ai_service_html/html__fast_api/schemas/dict/Schema__Dict__To__Text__Nodes__Response.py
mgraph_ai_service_html/html__fast_api/schemas/dict/Schema__Dict__To__Tree_View__Request.py
mgraph_ai_service_html/html__fast_api/schemas/hashes/Schema__Hashes__To__Html__Request.py
mgraph_ai_service_html/html__fast_api/schemas/html/Schema__Html__To__Dict__Hashes__Request.py
mgraph_ai_service_html/html__fast_api/schemas/html/Schema__Html__To__Dict__Hashes__Response.py
mgraph_ai_service_html/html__fast_api/schemas/html/Schema__Html__To__Dict__Request.py
mgraph_ai_service_html/html__fast_api/schemas/html/Schema__Html__To__Dict__Response.py
mgraph_ai_service_html/html__fast_api/schemas/html/Schema__Html__To__Html__Hashes__Request.py
mgraph_ai_service_html/html__fast_api/schemas/html/Schema__Html__To__Html__Request.py
mgraph_ai_service_html/html__fast_api/schemas/html/Schema__Html__To__Html__Xxx__Request.py
mgraph_ai_service_html/html__fast_api/schemas/html/Schema__Html__To__Text__Hashes__Request.py
mgraph_ai_service_html-0.6.24.dist-info/LICENSE
mgraph_ai_service_html-0.6.24.dist-info/METADATA
mgraph_ai_service_html-0.6.24.dist-info/WHEEL
mgraph_ai_service_html-0.6.24.dist-info/RECORD
